slurmtoppy/__init__.py
slurmtoppy/main.py
slurmtoppy-0.1.5.dist-info/LICENSE
slurmtoppy-0.1.5.dist-info/METADATA
slurmtoppy-0.1.5.dist-info/WHEEL
slurmtoppy-0.1.5.dist-info/entry_points.txt
slurmtoppy-0.1.5.dist-info/top_level.txt
slurmtoppy-0.1.5.dist-info/RECORD
