Metadata-Version: 2.1
Name: slurmtoppy
Version: 0.1.5
Summary: A console-based SLURM job monitoring tool
Home-page: https://github.com/ischurov/slurmtoppy
Author: Ilya V. Schurov
Author-email: ilya@schurov.com
License: MIT
Classifier: Programming Language :: Python :: 3
Classifier: License :: OSI Approved :: MIT License
Classifier: Operating System :: OS Independent
Requires-Python: >=3.9
License-File: LICENSE
